s_taper/__init__.py
s_taper/aio.py
s_taper/consts.py
S_Taper-0.8.3.6.dist-info/METADATA
S_Taper-0.8.3.6.dist-info/WHEEL
S_Taper-0.8.3.6.dist-info/top_level.txt
S_Taper-0.8.3.6.dist-info/RECORD
