Metadata-Version: 2.1
Name: S_Taper
Version: 0.8.3.6
Summary: Simple write-read add-on to SQLite3
Author: STaper_Admin
Classifier: Programming Language :: Python :: 3.10
Classifier: License :: OSI Approved :: MIT License
Classifier: Operating System :: OS Independent
Requires-Python: >=3.10
Requires-Dist: aiosqlite
